bysondb/__init__.py
bysondb/base.py
bysondb/db.py
bysondb/document_db.py
bysondb/errors.py
LICENSE
bysondb-0.1.1.dist-info/LICENSE
bysondb-0.1.1.dist-info/WHEEL
bysondb-0.1.1.dist-info/METADATA
bysondb-0.1.1.dist-info/RECORD
