Metadata-Version: 2.1
Name: bysondb
Version: 0.1.1
Summary: A simple BSON database written in Python
Home-page: https://github.com/AM2i9/bysondb
License: MIT
Keywords: bson,database,python
Author: Patrick Brennan
Requires-Python: >=3.9,<4.0
Classifier: License :: OSI Approved :: MIT License
Classifier: Programming Language :: Python :: 3
Classifier: Programming Language :: Python :: 3.9
Requires-Dist: bson (>=0.5.10,<0.6.0)
Project-URL: Repository, https://github.com/AM2i9/bysondb
